ssh_remote_control/__init__.py
ssh_remote_control/collection.py
ssh_remote_control/command.py
ssh_remote_control/errors.py
ssh_remote_control/event.py
ssh_remote_control/helpers.py
ssh_remote_control/locker.py
ssh_remote_control/manager.py
ssh_remote_control/sensor.py
ssh_remote_control/default_collections/__init__.py
ssh_remote_control/default_collections/const.py
ssh_remote_control/default_collections/linux.py
ssh_remote_control/default_collections/windows_cmd.py
ssh_remote_control/default_collections/windows_ps.py
ssh_remote_control-0.2.1.dist-info/LICENSE
ssh_remote_control-0.2.1.dist-info/METADATA
ssh_remote_control-0.2.1.dist-info/WHEEL
ssh_remote_control-0.2.1.dist-info/top_level.txt
ssh_remote_control-0.2.1.dist-info/RECORD
