Metadata-Version: 2.1
Name: ssh-remote-control
Version: 0.2.1
Summary: Control and monitor remote devices through SSH
Author-email: zhbjsh <zhbjsh@outlook.com>
Project-URL: Homepage, https://github.com/zhbjsh/ssh-remote-control
Project-URL: Bug Tracker, https://github.com/zhbjsh/ssh-remote-control/issues
Keywords: ssh,command line,remote control
Classifier: Programming Language :: Python :: 3
Classifier: License :: OSI Approved :: MIT License
Classifier: Operating System :: OS Independent
Requires-Python: >=3.10
License-File: LICENSE
Requires-Dist: async-timeout (>=4.0.2)
Requires-Dist: icmplib (>=3.0)
Requires-Dist: paramiko (>=3.2.0)
Requires-Dist: python-slugify (>=4.0.1)
Requires-Dist: wakeonlan (>=3.0.0)
